example/__init__.py
example/admin.py
example/apps.py
example/models.py
example/views.py
example/migrations/0001_initial.py
example/migrations/__init__.py
geoposition/__init__.py
geoposition/apps.py
geoposition/conf.py
geoposition/fields.py
geoposition/forms.py
geoposition/models.py
geoposition/widgets.py
geoposition/locale/ca/LC_MESSAGES/django.mo
geoposition/locale/ca/LC_MESSAGES/django.po
geoposition/locale/cs/LC_MESSAGES/django.mo
geoposition/locale/cs/LC_MESSAGES/django.po
geoposition/locale/es/LC_MESSAGES/django.mo
geoposition/locale/es/LC_MESSAGES/django.po
geoposition/locale/ru/LC_MESSAGES/django.mo
geoposition/locale/ru/LC_MESSAGES/django.po
geoposition/static/geoposition/geoposition.css
geoposition/static/geoposition/google.js
geoposition/static/geoposition/leaflet.js
geoposition/templates/geoposition/widgets/geoposition.html
geoposition/tests/__init__.py
geoposition/tests/settings.py
geoposition/tests/test_geoposition.py
geoposition/tests/urls.py
django_geoposition_2-0.4.0.dist-info/AUTHORS
django_geoposition_2-0.4.0.dist-info/LICENSE
django_geoposition_2-0.4.0.dist-info/METADATA
django_geoposition_2-0.4.0.dist-info/WHEEL
django_geoposition_2-0.4.0.dist-info/top_level.txt
django_geoposition_2-0.4.0.dist-info/RECORD
