Metadata-Version: 2.1
Name: django-geoposition-2
Version: 0.4.0
Summary: Django model field that can hold a geoposition, and corresponding admin widget.
Home-page: http://github.com/imdario/django-geoposition
Author: Dario Castañé
Author-email: i@dario.im
Classifier: Development Status :: 4 - Beta
Classifier: Environment :: Web Environment
Classifier: Intended Audience :: Developers
Classifier: License :: OSI Approved :: BSD License
Classifier: Operating System :: OS Independent
Classifier: Programming Language :: Python
Classifier: Programming Language :: Python :: 3
Classifier: Programming Language :: Python :: 3.4
Classifier: Programming Language :: Python :: 3.5
Classifier: Programming Language :: Python :: 3.6
Classifier: Programming Language :: Python :: 3.7
Classifier: Programming Language :: Python :: 3.8
Classifier: Framework :: Django
License-File: LICENSE
License-File: AUTHORS
